{
   "@collapsed" : false,
   "@configType" : "BIOME",
   "@name" : "SinkHoles",
   "@position" : [ 7368, 8082 ],
   "@scroll" : [ 8890.818359375, 8940.7890625, 0.5 ],
   "@toggle-test" : false,
   "@toggle-world" : true,
   "@unlinked" : [],
   "@version" : 11,
   "biome" : {
      "fun" : {
         "@collapsed" : false,
         "@name" : "SinkHoles",
         "@position" : [ 7844, 8385 ],
         "altitude" : {
            "enabled" : true,
            "value" : 0.52600002288818359
         },
         "humidity" : {
            "enabled" : true,
            "value" : 0.53100001811981201
         },
         "nameStyle" : "{} Chasma",
         "part" : {
            "@collapsed" : false,
            "@name" : "SinkHoles",
            "@position" : [ 8316, 8130 ],
            "@selector-open" : false,
            "@toggle-caves" : true,
            "@toggle-ccaves" : true,
            "@toggle-csurface" : true,
            "@toggle-cthreed" : true,
            "@toggle-data" : true,
            "@toggle-drop" : false,
            "@toggle-heightmap" : true,
            "@toggle-selector" : false,
            "@toggle-stage" : true,
            "@toggle-threed" : false,
            "@toggle-visualise" : true,
            "@x-name" : "x",
            "@y-name" : "y",
            "caveSurfaceShrink" : {
               "enabled" : true,
               "value" : 1
            },
            "caveThresholdBias" : {
               "enabled" : true,
               "value" : 0
            },
            "caves" : {
               "@collapsed" : false,
               "@name" : "Layered 3D",
               "@position" : [ 8788, 7864 ],
               "components" : [
                  {
                     "fun" : {
                        "@collapsed" : false,
                        "@name" : "CrookedCaves",
                        "@position" : [ 9082, 7854 ],
                        "frequency" : [ 1, 1, 1 ],
                        "links" : [],
                        "offset" : [ 637.54052734375, 1.4974601268768311, -40.106689453125 ],
                        "offset-hash" : "3n7ZJ20GXHK8GBFY",
                        "reference" : "noise3d/CrookedCaves.json",
                        "tick" : 0,
                        "type" : "reference"
                     },
                     "y" : 65.782005310058594
                  },
                  {
                     "fun" : {
                        "@collapsed" : false,
                        "@name" : "Constant 3D",
                        "@position" : [ 9082, 7983 ],
                        "frequency" : [ 1, 1, 1 ],
                        "offset" : [ -87.837066650390625, -10.911374092102051, -305.50784301757813 ],
                        "offset-hash" : "DzDeBY15C7XUW7px",
                        "type" : "constant",
                        "value" : 0
                     },
                     "y" : 73.215003967285156
                  }
               ],
               "frequency" : [ 1, 1, 1 ],
               "type" : "layered"
            },
            "caves_decorations" : null,
            "caves_substrate" : null,
            "distortion" : null,
            "distortionStrength" : {
               "enabled" : false,
               "value" : 0
            },
            "drop" : null,
            "dropMaxDepth" : {
               "enabled" : false,
               "value" : 0
            },
            "dropMaxGradient" : {
               "enabled" : false,
               "value" : 0
            },
            "dropMaxNoGravel" : {
               "enabled" : false,
               "value" : 0
            },
            "heightmap" : {
               "@collapsed" : false,
               "@name" : "Sum 2D",
               "@position" : [ 8788, 7250 ],
               "frequency" : [ 1, 1 ],
               "terms" : [
                  {
                     "fun" : {
                        "@collapsed" : false,
                        "@name" : "Absolute 2D",
                        "@position" : [ 9121, 7048 ],
                        "frequency" : [ 1, 1 ],
                        "fun" : {
                           "@collapsed" : false,
                           "@name" : "Ditches",
                           "@position" : [ 9408, 7011 ],
                           "frequency" : [ 1, 1 ],
                           "links" : [
                              {
                                 "linkPath" : [
                                    {
                                       "index" : -1,
                                       "name" : "noise2d"
                                    },
                                    {
                                       "index" : -1,
                                       "name" : "fun"
                                    },
                                    {
                                       "index" : -1,
                                       "name" : "terms"
                                    },
                                    {
                                       "index" : 0,
                                       "name" : ""
                                    },
                                    {
                                       "index" : -1,
                                       "name" : "fun"
                                    },
                                    {
                                       "index" : -1,
                                       "name" : "min"
                                    }
                                 ],
                                 "linkType" : "LT:CUSTOM_SLIDER",
                                 "sliderValue" : -2
                              },
                              {
                                 "linkPath" : [
                                    {
                                       "index" : -1,
                                       "name" : "noise2d"
                                    },
                                    {
                                       "index" : -1,
                                       "name" : "fun"
                                    },
                                    {
                                       "index" : -1,
                                       "name" : "terms"
                                    },
                                    {
                                       "index" : 0,
                                       "name" : ""
                                    },
                                    {
                                       "index" : -1,
                                       "name" : "fun"
                                    },
                                    {
                                       "index" : -1,
                                       "name" : "fun"
                                    },
                                    {
                                       "index" : -1,
                                       "name" : "fun"
                                    },
                                    {
                                       "index" : -1,
                                       "name" : "base"
                                    },
                                    {
                                       "index" : -1,
                                       "name" : "cellScale"
                                    }
                                 ],
                                 "linkType" : "LT:CUSTOM_SLIDER",
                                 "sliderValue" : 5.5
                              },
                              {
                                 "linkPath" : [
                                    {
                                       "index" : -1,
                                       "name" : "noise2d"
                                    },
                                    {
                                       "index" : -1,
                                       "name" : "fun"
                                    },
                                    {
                                       "index" : -1,
                                       "name" : "terms"
                                    },
                                    {
                                       "index" : 0,
                                       "name" : ""
                                    },
                                    {
                                       "index" : -1,
                                       "name" : "fun"
                                    },
                                    {
                                       "index" : -1,
                                       "name" : "fun"
                                    },
                                    {
                                       "index" : -1,
                                       "name" : "fun"
                                    },
                                    {
                                       "index" : -1,
                                       "name" : "distortion"
                                    },
                                    {
                                       "index" : -1,
                                       "name" : "frequency"
                                    },
                                    {
                                       "index" : -1,
                                       "name" : "@xz"
                                    }
                                 ],
                                 "linkType" : "LT:CUSTOM_SLIDER",
                                 "sliderValue" : 1
                              }
                           ],
                           "offset" : [ 317.51583862304688, 366.33047485351563 ],
                           "offset-hash" : "GXEbQl2WhE6mwtWX",
                           "reference" : "noise2d/Heightmaps/Ditches.json",
                           "tick" : 0,
                           "type" : "reference"
                        },
                        "type" : "absolute"
                     },
                     "multiplier" : 0.84900003671646118,
                     "power" : 1
                  },
                  {
                     "fun" : {
                        "@collapsed" : false,
                        "@name" : "Constant 2D",
                        "@position" : [ 9121, 7185 ],
                        "frequency" : [ 1, 1 ],
                        "offset" : [ -276.82916259765625, 321.15682983398438 ],
                        "offset-hash" : "6qIPujHIsn6speZx",
                        "type" : "constant",
                        "value" : -0.86500006914138794
                     },
                     "multiplier" : 1,
                     "power" : 1
                  },
                  {
                     "fun" : {
                        "@collapsed" : false,
                        "@name" : "Max 2D",
                        "@position" : [ 9121, 7505 ],
                        "frequency" : [ 1, 1 ],
                        "terms" : [
                           {
                              "@collapsed" : false,
                              "@name" : "Sum 2D",
                              "@position" : [ 9434, 7338 ],
                              "frequency" : [ 1, 1 ],
                              "terms" : [
                                 {
                                    "fun" : {
                                       "@collapsed" : false,
                                       "@name" : "Absolute 2D",
                                       "@position" : [ 9738, 7352 ],
                                       "frequency" : [ 1, 1 ],
                                       "fun" : {
                                          "@collapsed" : false,
                                          "@name" : "Ditches",
                                          "@position" : [ 10025, 7315 ],
                                          "frequency" : [ 1, 1 ],
                                          "links" : [
                                             {
                                                "linkPath" : [
                                                   {
                                                      "index" : -1,
                                                      "name" : "noise2d"
                                                   },
                                                   {
                                                      "index" : -1,
                                                      "name" : "fun"
                                                   },
                                                   {
                                                      "index" : -1,
                                                      "name" : "terms"
                                                   },
                                                   {
                                                      "index" : 0,
                                                      "name" : ""
                                                   },
                                                   {
                                                      "index" : -1,
                                                      "name" : "fun"
                                                   },
                                                   {
                                                      "index" : -1,
                                                      "name" : "min"
                                                   }
                                                ],
                                                "linkType" : "LT:CUSTOM_SLIDER",
                                                "sliderValue" : -2
                                             },
                                             {
                                                "linkPath" : [
                                                   {
                                                      "index" : -1,
                                                      "name" : "noise2d"
                                                   },
                                                   {
                                                      "index" : -1,
                                                      "name" : "fun"
                                                   },
                                                   {
                                                      "index" : -1,
                                                      "name" : "terms"
                                                   },
                                                   {
                                                      "index" : 0,
                                                      "name" : ""
                                                   },
                                                   {
                                                      "index" : -1,
                                                      "name" : "fun"
                                                   },
                                                   {
                                                      "index" : -1,
                                                      "name" : "fun"
                                                   },
                                                   {
                                                      "index" : -1,
                                                      "name" : "fun"
                                                   },
                                                   {
                                                      "index" : -1,
                                                      "name" : "base"
                                                   },
                                                   {
                                                      "index" : -1,
                                                      "name" : "cellScale"
                                                   }
                                                ],
                                                "linkType" : "LT:CUSTOM_SLIDER",
                                                "sliderValue" : 5.5
                                             },
                                             {
                                                "linkPath" : [
                                                   {
                                                      "index" : -1,
                                                      "name" : "noise2d"
                                                   },
                                                   {
                                                      "index" : -1,
                                                      "name" : "fun"
                                                   },
                                                   {
                                                      "index" : -1,
                                                      "name" : "terms"
                                                   },
                                                   {
                                                      "index" : 0,
                                                      "name" : ""
                                                   },
                                                   {
                                                      "index" : -1,
                                                      "name" : "fun"
                                                   },
                                                   {
                                                      "index" : -1,
                                                      "name" : "fun"
                                                   },
                                                   {
                                                      "index" : -1,
                                                      "name" : "fun"
                                                   },
                                                   {
                                                      "index" : -1,
                                                      "name" : "distortion"
                                                   },
                                                   {
                                                      "index" : -1,
                                                      "name" : "frequency"
                                                   },
                                                   {
                                                      "index" : -1,
                                                      "name" : "@xz"
                                                   }
                                                ],
                                                "linkType" : "LT:CUSTOM_SLIDER",
                                                "sliderValue" : 1
                                             }
                                          ],
                                          "offset" : [ 317.51583862304688, 366.33047485351563 ],
                                          "offset-hash" : "GXEbQl2WhE6mwtWX",
                                          "reference" : "noise2d/Heightmaps/Ditches.json",
                                          "tick" : 0,
                                          "type" : "reference"
                                       },
                                       "type" : "absolute"
                                    },
                                    "multiplier" : 1,
                                    "power" : 1
                                 },
                                 {
                                    "fun" : {
                                       "@collapsed" : false,
                                       "@name" : "Constant 2D",
                                       "@position" : [ 9738, 7490 ],
                                       "frequency" : [ 1, 1 ],
                                       "offset" : [ -276.82916259765625, 321.15682983398438 ],
                                       "offset-hash" : "6qIPujHIsn6speZx",
                                       "type" : "constant",
                                       "value" : -0.90800005197525024
                                    },
                                    "multiplier" : 1,
                                    "power" : 1
                                 },
                                 {
                                    "fun" : {
                                       "@collapsed" : false,
                                       "@name" : "Perlin 2D",
                                       "@position" : [ 9738, 7619 ],
                                       "frequency" : [ 0.53200000524520874, 0.53200000524520874 ],
                                       "offset" : [ -183.17539978027344, 257.05828857421875 ],
                                       "offset-hash" : "7ofummDecI3m7gJF",
                                       "type" : "perlin"
                                    },
                                    "multiplier" : 0.095000006258487701,
                                    "power" : 1
                                 }
                              ],
                              "type" : "sum"
                           },
                           {
                              "@collapsed" : false,
                              "@name" : "Constant 2D",
                              "@position" : [ 9434, 7724 ],
                              "frequency" : [ 1, 1 ],
                              "offset" : [ 319.481201171875, 379.83905029296875 ],
                              "offset-hash" : "vKMD9Xprx0GNHIfR",
                              "type" : "constant",
                              "value" : 0
                           }
                        ],
                        "type" : "max"
                     },
                     "multiplier" : 0.87500005960464478,
                     "power" : 1
                  }
               ],
               "type" : "sum"
            },
            "heightmapMaxY" : {
               "enabled" : false,
               "value" : 256
            },
            "heightmapMinY" : {
               "enabled" : false,
               "value" : 0
            },
            "parts" : [],
            "shrink" : null,
            "strata" : {
               "@collapsed" : false,
               "@name" : "Join Strata",
               "@position" : [ 8788, 8200 ],
               "components" : [
                  {
                     "@collapsed" : false,
                     "@name" : "Fill1",
                     "@position" : [ 9084, 8134 ],
                     "links" : [],
                     "reference" : "strata/Fill1.json",
                     "tick" : 0,
                     "type" : "reference"
                  },
                  {
                     "@collapsed" : false,
                     "@name" : "Fill2",
                     "@position" : [ 9084, 8194 ],
                     "links" : [],
                     "reference" : "strata/Fill2.json",
                     "tick" : 0,
                     "type" : "reference"
                  },
                  {
                     "@collapsed" : false,
                     "@name" : "Fill3",
                     "@position" : [ 9084, 8254 ],
                     "links" : [],
                     "reference" : "strata/Fill3.json",
                     "tick" : 0,
                     "type" : "reference"
                  },
                  {
                     "@collapsed" : false,
                     "@name" : "Fill4",
                     "@position" : [ 9084, 8314 ],
                     "links" : [],
                     "reference" : "strata/Fill4.json",
                     "tick" : 0,
                     "type" : "reference"
                  },
                  {
                     "@collapsed" : false,
                     "@name" : "Fill5",
                     "@position" : [ 9084, 8374 ],
                     "links" : [],
                     "reference" : "strata/Fill5.json",
                     "tick" : 0,
                     "type" : "reference"
                  }
               ],
               "type" : "join"
            },
            "surface_decorations" : {
               "@collapsed" : false,
               "@name" : "Standard Decorations",
               "@position" : [ 8788, 9448 ],
               "@toggle-ceiling" : false,
               "@toggle-floor" : true,
               "ceiling" : [],
               "floor" : [
                  {
                     "clearance" : 8,
                     "constraintType" : [
                        "GRASS_VERDANT_BASE/SOIL_CLAY_BASE",
                        "GRASS_VERDANT_BASE/SOIL_PEATY_BASE"
                     ],
                     "density" : -0.37000000476837158,
                     "depth" : 8,
                     "instance" : {
                        "@collapsed" : false,
                        "@name" : "Bush (deprecated)",
                        "@position" : [ 9099, 9453 ],
                        "blockType" : "WOOD_LUSH_LEAVES",
                        "height" : 1,
                        "maxScale" : 2,
                        "minScale" : 0.5,
                        "radius" : 6,
                        "stemType" : "WOOD_LUSH_LEAVES",
                        "taper" : 2,
                        "type" : "bush"
                     },
                     "maxGradient" : 5,
                     "maxSize" : 1,
                     "maxY" : 256,
                     "minGradient" : 3,
                     "minSize" : 0,
                     "minY" : 74,
                     "noise" : {
                        "@collapsed" : false,
                        "@name" : "Remap 2D",
                        "@position" : [ 9099, 9718 ],
                        "clamp" : true,
                        "clampPower" : 10,
                        "frequency" : [ 1, 1 ],
                        "fun" : {
                           "@collapsed" : false,
                           "@name" : "Remap 2D",
                           "@position" : [ 9395, 9718 ],
                           "clamp" : true,
                           "clampPower" : 10,
                           "frequency" : [ 1, 1 ],
                           "fun" : {
                              "@collapsed" : false,
                              "@name" : "Sum 2D",
                              "@position" : [ 9691, 9673 ],
                              "frequency" : [ 1, 1 ],
                              "terms" : [
                                 {
                                    "fun" : {
                                       "@collapsed" : false,
                                       "@name" : "Ditches",
                                       "@position" : [ 9987, 9663 ],
                                       "frequency" : [ 0.77500003576278687, 0.77500003576278687 ],
                                       "links" : [
                                          {
                                             "linkPath" : [
                                                {
                                                   "index" : -1,
                                                   "name" : "noise2d"
                                                },
                                                {
                                                   "index" : -1,
                                                   "name" : "fun"
                                                },
                                                {
                                                   "index" : -1,
                                                   "name" : "terms"
                                                },
                                                {
                                                   "index" : 0,
                                                   "name" : ""
                                                },
                                                {
                                                   "index" : -1,
                                                   "name" : "fun"
                                                },
                                                {
                                                   "index" : -1,
                                                   "name" : "min"
                                                }
                                             ],
                                             "linkType" : "LT:CUSTOM_SLIDER",
                                             "sliderValue" : -2
                                          },
                                          {
                                             "linkPath" : [
                                                {
                                                   "index" : -1,
                                                   "name" : "noise2d"
                                                },
                                                {
                                                   "index" : -1,
                                                   "name" : "fun"
                                                },
                                                {
                                                   "index" : -1,
                                                   "name" : "terms"
                                                },
                                                {
                                                   "index" : 0,
                                                   "name" : ""
                                                },
                                                {
                                                   "index" : -1,
                                                   "name" : "fun"
                                                },
                                                {
                                                   "index" : -1,
                                                   "name" : "fun"
                                                },
                                                {
                                                   "index" : -1,
                                                   "name" : "fun"
                                                },
                                                {
                                                   "index" : -1,
                                                   "name" : "base"
                                                },
                                                {
                                                   "index" : -1,
                                                   "name" : "cellScale"
                                                }
                                             ],
                                             "linkType" : "LT:CUSTOM_SLIDER",
                                             "sliderValue" : 8
                                          },
                                          {
                                             "linkPath" : [
                                                {
                                                   "index" : -1,
                                                   "name" : "noise2d"
                                                },
                                                {
                                                   "index" : -1,
                                                   "name" : "fun"
                                                },
                                                {
                                                   "index" : -1,
                                                   "name" : "terms"
                                                },
                                                {
                                                   "index" : 0,
                                                   "name" : ""
                                                },
                                                {
                                                   "index" : -1,
                                                   "name" : "fun"
                                                },
                                                {
                                                   "index" : -1,
                                                   "name" : "fun"
                                                },
                                                {
                                                   "index" : -1,
                                                   "name" : "fun"
                                                },
                                                {
                                                   "index" : -1,
                                                   "name" : "distortion"
                                                },
                                                {
                                                   "index" : -1,
                                                   "name" : "frequency"
                                                },
                                                {
                                                   "index" : -1,
                                                   "name" : "@xz"
                                                }
                                             ],
                                             "linkType" : "LT:CUSTOM_SLIDER",
                                             "sliderValue" : 0.12600000202655792
                                          }
                                       ],
                                       "offset" : [ -103.05943298339844, 61.666439056396484 ],
                                       "offset-hash" : "Kd4RC7kMUiKmP39d",
                                       "reference" : "noise2d/Heightmaps/Ditches.json",
                                       "tick" : 0,
                                       "type" : "reference"
                                    },
                                    "multiplier" : -1,
                                    "power" : 1
                                 },
                                 {
                                    "fun" : {
                                       "@collapsed" : false,
                                       "@name" : "Constant 2D",
                                       "@position" : [ 9987, 9838 ],
                                       "frequency" : [ 1, 1 ],
                                       "offset" : [ -170.65080261230469, 156.39212036132813 ],
                                       "offset-hash" : "IygjzaWrzolH6AcY",
                                       "type" : "constant",
                                       "value" : -0.21800000965595245
                                    },
                                    "multiplier" : 1,
                                    "power" : 1
                                 }
                              ],
                              "type" : "sum"
                           },
                           "max" : 2,
                           "min" : -2,
                           "type" : "remap"
                        },
                        "max" : 2,
                        "min" : -2,
                        "type" : "remap"
                     },
                     "placementType" : "FLORA_FLOWER_1",
                     "sizeNoise" : null,
                     "smooth" : false,
                     "threshold" : 0
                  }
               ],
               "type" : "standard"
            },
            "surface_substrate" : {
               "@collapsed" : false,
               "@name" : "Standard Substrate",
               "@position" : [ 8788, 8434 ],
               "strates" : [
                  {
                     "averageDepth" : 3,
                     "blockType" : "GRASS_VERDANT_BASE/SOIL_PEATY_BASE",
                     "depthNoise" : {
                        "@collapsed" : false,
                        "@name" : "Perlin 2D",
                        "@position" : [ 9093, 8729 ],
                        "frequency" : [ 1, 1 ],
                        "offset" : [ -391.5526123046875, -283.49493408203125 ],
                        "offset-hash" : "eOnm2yo7kTcW7QTr",
                        "type" : "perlin"
                     },
                     "depthNoiseScale" : 6,
                     "maxGradient" : 5,
                     "maxY" : 256,
                     "metadata" : {
                        "@toggle-metadata" : true,
                        "maxGradient" : 5,
                        "maxThreshold" : 1,
                        "maxY" : 256,
                        "minGradient" : 0,
                        "minThreshold" : -1,
                        "minY" : 0,
                        "noise" : {
                           "@collapsed" : false,
                           "@name" : "Perlin 2D",
                           "@position" : [ 9093, 8835 ],
                           "frequency" : [ 1, 1 ],
                           "offset" : [ -71.393913269042969, -233.91595458984375 ],
                           "offset-hash" : "vfKUd1LeyNQkxZRE",
                           "type" : "perlin"
                        }
                     },
                     "minGradient" : 0,
                     "minY" : 0
                  },
                  {
                     "averageDepth" : 3,
                     "blockType" : "GRASS_VERDANT_BASE/SOIL_CLAY_BASE",
                     "depthNoise" : {
                        "@collapsed" : false,
                        "@name" : "Perlin 2D",
                        "@position" : [ 9093, 8941 ],
                        "frequency" : [ 1, 1 ],
                        "offset" : [ 161.94705200195313, -330.5015869140625 ],
                        "offset-hash" : "AIGhRCqESy8alDUl",
                        "type" : "perlin"
                     },
                     "depthNoiseScale" : 6,
                     "maxGradient" : 5,
                     "maxY" : 256,
                     "metadata" : {
                        "@toggle-metadata" : true,
                        "maxGradient" : 5,
                        "maxThreshold" : 1,
                        "maxY" : 256,
                        "minGradient" : 0,
                        "minThreshold" : -1,
                        "minY" : 0,
                        "noise" : {
                           "@collapsed" : false,
                           "@name" : "Perlin 2D",
                           "@position" : [ 9093, 9047 ],
                           "frequency" : [ 1, 1 ],
                           "offset" : [ -360.7171630859375, 44.172367095947266 ],
                           "offset-hash" : "OJ8w10KkTsL3D1GY",
                           "type" : "perlin"
                        }
                     },
                     "minGradient" : 0,
                     "minY" : 0
                  },
                  {
                     "averageDepth" : 3,
                     "blockType" : "GRAVEL_DEFAULT_BASE",
                     "depthNoise" : null,
                     "depthNoiseScale" : 6,
                     "maxGradient" : 5,
                     "maxY" : 256,
                     "metadata" : {
                        "@toggle-metadata" : true,
                        "maxGradient" : 5,
                        "maxThreshold" : 1,
                        "maxY" : 256,
                        "minGradient" : 0,
                        "minThreshold" : -1,
                        "minY" : 0,
                        "noise" : null
                     },
                     "minGradient" : 0,
                     "minY" : 0
                  }
               ],
               "type" : "standard"
            },
            "threeD" : null,
            "threeDMaxY" : {
               "enabled" : false,
               "value" : 256
            },
            "threeDMinY" : {
               "enabled" : false,
               "value" : 0
            },
            "threeDSurfaceMaxY" : {
               "enabled" : false,
               "value" : 256
            },
            "threeDSurfaceMinY" : {
               "enabled" : false,
               "value" : 0
            },
            "threeDThresholdBias" : {
               "enabled" : false,
               "value" : -1
            },
            "threed_decorations" : null,
            "threed_substrate" : null,
            "x" : null,
            "y" : null
         },
         "temperature" : {
            "enabled" : true,
            "value" : 0.52600002288818359
         },
         "vegetation" : {
            "enabled" : true,
            "value" : 0.23800000548362732
         },
         "weight" : 0.5
      },
      "links" : [
         {
            "blockConstraint" : 3274820576,
            "blockDefault" : "",
            "checkDefault" : false,
            "linkPath" : [
               {
                  "index" : -1,
                  "name" : "biome"
               },
               {
                  "index" : -1,
                  "name" : "fun"
               },
               {
                  "index" : -1,
                  "name" : "weight"
               }
            ],
            "linkType" : "LT:CUSTOM_SLIDER",
            "name" : "Biome Weight",
            "shortPath" : "SinkHoles.weight",
            "sliderCheck" : false,
            "sliderDefault" : 0.5,
            "sliderMax" : 1,
            "sliderMin" : 0,
            "sliderStep" : 0.0010000000474974513
         }
      ]
   },
   "generator" : {
      "@version" : 6,
      "biomeSize" : 24,
      "lowerSea" : {
         "level" : 16,
         "liquidType" : "WATER"
      },
      "sea" : {
         "level" : 64,
         "liquidType" : "WATER"
      }
   },
   "seed" : "I has a seed!",
   "sharedConfig" : {
      "blockColors" : {
         "ASH_DEFAULT_BASE" : 1,
         "CRYSTAL_GLEAM_BASE" : 13,
         "FLORA_FLOWER_1" : 1,
         "FLORA_FLOWER_2" : 1,
         "FLORA_FLOWER_3" : 1,
         "FLORA_FLOWER_4" : 1,
         "FLORA_PLANT_FIBROUS" : 1,
         "FLORA_PLANT_INKY" : 1,
         "GRASS_BARBED_BASE" : 8,
         "GRASS_GNARLED_BASE" : 7,
         "GRASS_VERDANT_BASE" : 9,
         "GRAVEL_DEFAULT_BASE" : 5,
         "GROWTH_DEFAULT_BASE" : 1,
         "MOULD_DEFAULT_BASE" : 1,
         "MUD_DEFAULT_BASE" : 1,
         "ROCK_IGNEOUS_BASE" : 4,
         "ROCK_METAMORPHIC_BASE" : 5,
         "ROCK_SEDIMENTARY_BASE" : 6,
         "SAND_DEFAULT_BASE" : 16,
         "SOIL_CLAY_BASE" : 1,
         "SOIL_PEATY_BASE" : 3,
         "SOIL_SILTY_BASE" : 2,
         "SPONGE_DEFAULT_BASE" : 1,
         "TANGLE_DEFAULT_BASE" : 1,
         "THORNS_DEFAULT_BASE" : 1,
         "WOOD_ANCIENT_TRUNK" : 10,
         "WOOD_EXOTIC_LEAVES" : 15,
         "WOOD_LUSH_LEAVES" : 13,
         "WOOD_LUSTROUS_TRUNK" : 1,
         "WOOD_TWISTED_TRUNK" : 11,
         "WOOD_WAXY_LEAVES" : 13
      },
      "worldSize" : 288
   },
   "test" : {
      "@collapsed" : false,
      "@name" : "Reference Biome",
      "@position" : [ 7844, 9969 ],
      "embedded" : {
         "@collapsed" : false,
         "@configType" : "BIOME",
         "@name" : "SinkHoles",
         "@position" : [ 7368, 8082 ],
         "@toggle-test" : false,
         "@toggle-world" : true,
         "@version" : 11,
         "biome" : {
            "fun" : {
               "@collapsed" : false,
               "@name" : "SinkHoles",
               "@position" : [ 7844, 8385 ],
               "altitude" : {
                  "enabled" : true,
                  "value" : 0.52600002288818359
               },
               "humidity" : {
                  "enabled" : true,
                  "value" : 0.53100001811981201
               },
               "nameStyle" : "{} Chasma",
               "part" : {
                  "@collapsed" : false,
                  "@name" : "SinkHoles",
                  "@position" : [ 8316, 8130 ],
                  "@selector-open" : false,
                  "@toggle-caves" : true,
                  "@toggle-ccaves" : true,
                  "@toggle-csurface" : true,
                  "@toggle-cthreed" : true,
                  "@toggle-data" : true,
                  "@toggle-drop" : false,
                  "@toggle-heightmap" : true,
                  "@toggle-selector" : false,
                  "@toggle-stage" : true,
                  "@toggle-threed" : false,
                  "@toggle-visualise" : true,
                  "@x-name" : "x",
                  "@y-name" : "y",
                  "caveSurfaceShrink" : {
                     "enabled" : true,
                     "value" : 1
                  },
                  "caveThresholdBias" : {
                     "enabled" : true,
                     "value" : 0
                  },
                  "caves" : {
                     "@collapsed" : false,
                     "@name" : "Layered 3D",
                     "@position" : [ 8788, 7864 ],
                     "components" : [
                        {
                           "fun" : {
                              "@collapsed" : false,
                              "@name" : "CrookedCaves",
                              "@position" : [ 9082, 7854 ],
                              "frequency" : [ 1, 1, 1 ],
                              "links" : [],
                              "offset" : [ 637.54052734375, 1.4974601268768311, -40.106689453125 ],
                              "offset-hash" : "3n7ZJ20GXHK8GBFY",
                              "reference" : "noise3d/CrookedCaves.json",
                              "tick" : 0,
                              "type" : "reference"
                           },
                           "y" : 65.782005310058594
                        },
                        {
                           "fun" : {
                              "@collapsed" : false,
                              "@name" : "Constant 3D",
                              "@position" : [ 9082, 7983 ],
                              "frequency" : [ 1, 1, 1 ],
                              "offset" : [ -87.837066650390625, -10.911374092102051, -305.50784301757813 ],
                              "offset-hash" : "DzDeBY15C7XUW7px",
                              "type" : "constant",
                              "value" : 0
                           },
                           "y" : 73.215003967285156
                        }
                     ],
                     "frequency" : [ 1, 1, 1 ],
                     "type" : "layered"
                  },
                  "caves_decorations" : null,
                  "caves_substrate" : null,
                  "distortion" : null,
                  "distortionStrength" : {
                     "enabled" : false,
                     "value" : 0
                  },
                  "drop" : null,
                  "dropMaxDepth" : {
                     "enabled" : false,
                     "value" : 0
                  },
                  "dropMaxGradient" : {
                     "enabled" : false,
                     "value" : 0
                  },
                  "dropMaxNoGravel" : {
                     "enabled" : false,
                     "value" : 0
                  },
                  "heightmap" : {
                     "@collapsed" : false,
                     "@name" : "Sum 2D",
                     "@position" : [ 8788, 7250 ],
                     "frequency" : [ 1, 1 ],
                     "terms" : [
                        {
                           "fun" : {
                              "@collapsed" : false,
                              "@name" : "Absolute 2D",
                              "@position" : [ 9121, 7048 ],
                              "frequency" : [ 1, 1 ],
                              "fun" : {
                                 "@collapsed" : false,
                                 "@name" : "Ditches",
                                 "@position" : [ 9408, 7011 ],
                                 "frequency" : [ 1, 1 ],
                                 "links" : [
                                    {
                                       "linkPath" : [
                                          {
                                             "index" : -1,
                                             "name" : "noise2d"
                                          },
                                          {
                                             "index" : -1,
                                             "name" : "fun"
                                          },
                                          {
                                             "index" : -1,
                                             "name" : "terms"
                                          },
                                          {
                                             "index" : 0,
                                             "name" : ""
                                          },
                                          {
                                             "index" : -1,
                                             "name" : "fun"
                                          },
                                          {
                                             "index" : -1,
                                             "name" : "min"
                                          }
                                       ],
                                       "linkType" : "LT:CUSTOM_SLIDER",
                                       "sliderValue" : -2
                                    },
                                    {
                                       "linkPath" : [
                                          {
                                             "index" : -1,
                                             "name" : "noise2d"
                                          },
                                          {
                                             "index" : -1,
                                             "name" : "fun"
                                          },
                                          {
                                             "index" : -1,
                                             "name" : "terms"
                                          },
                                          {
                                             "index" : 0,
                                             "name" : ""
                                          },
                                          {
                                             "index" : -1,
                                             "name" : "fun"
                                          },
                                          {
                                             "index" : -1,
                                             "name" : "fun"
                                          },
                                          {
                                             "index" : -1,
                                             "name" : "fun"
                                          },
                                          {
                                             "index" : -1,
                                             "name" : "base"
                                          },
                                          {
                                             "index" : -1,
                                             "name" : "cellScale"
                                          }
                                       ],
                                       "linkType" : "LT:CUSTOM_SLIDER",
                                       "sliderValue" : 5.5
                                    },
                                    {
                                       "linkPath" : [
                                          {
                                             "index" : -1,
                                             "name" : "noise2d"
                                          },
                                          {
                                             "index" : -1,
                                             "name" : "fun"
                                          },
                                          {
                                             "index" : -1,
                                             "name" : "terms"
                                          },
                                          {
                                             "index" : 0,
                                             "name" : ""
                                          },
                                          {
                                             "index" : -1,
                                             "name" : "fun"
                                          },
                                          {
                                             "index" : -1,
                                             "name" : "fun"
                                          },
                                          {
                                             "index" : -1,
                                             "name" : "fun"
                                          },
                                          {
                                             "index" : -1,
                                             "name" : "distortion"
                                          },
                                          {
                                             "index" : -1,
                                             "name" : "frequency"
                                          },
                                          {
                                             "index" : -1,
                                             "name" : "@xz"
                                          }
                                       ],
                                       "linkType" : "LT:CUSTOM_SLIDER",
                                       "sliderValue" : 1
                                    }
                                 ],
                                 "offset" : [ 317.51583862304688, 366.33047485351563 ],
                                 "offset-hash" : "GXEbQl2WhE6mwtWX",
                                 "reference" : "noise2d/Heightmaps/Ditches.json",
                                 "tick" : 0,
                                 "type" : "reference"
                              },
                              "type" : "absolute"
                           },
                           "multiplier" : 0.84900003671646118,
                           "power" : 1
                        },
                        {
                           "fun" : {
                              "@collapsed" : false,
                              "@name" : "Constant 2D",
                              "@position" : [ 9121, 7185 ],
                              "frequency" : [ 1, 1 ],
                              "offset" : [ -276.82916259765625, 321.15682983398438 ],
                              "offset-hash" : "6qIPujHIsn6speZx",
                              "type" : "constant",
                              "value" : -0.86500006914138794
                           },
                           "multiplier" : 1,
                           "power" : 1
                        },
                        {
                           "fun" : {
                              "@collapsed" : false,
                              "@name" : "Max 2D",
                              "@position" : [ 9121, 7505 ],
                              "frequency" : [ 1, 1 ],
                              "terms" : [
                                 {
                                    "@collapsed" : false,
                                    "@name" : "Sum 2D",
                                    "@position" : [ 9434, 7338 ],
                                    "frequency" : [ 1, 1 ],
                                    "terms" : [
                                       {
                                          "fun" : {
                                             "@collapsed" : false,
                                             "@name" : "Absolute 2D",
                                             "@position" : [ 9738, 7352 ],
                                             "frequency" : [ 1, 1 ],
                                             "fun" : {
                                                "@collapsed" : false,
                                                "@name" : "Ditches",
                                                "@position" : [ 10025, 7315 ],
                                                "frequency" : [ 1, 1 ],
                                                "links" : [
                                                   {
                                                      "linkPath" : [
                                                         {
                                                            "index" : -1,
                                                            "name" : "noise2d"
                                                         },
                                                         {
                                                            "index" : -1,
                                                            "name" : "fun"
                                                         },
                                                         {
                                                            "index" : -1,
                                                            "name" : "terms"
                                                         },
                                                         {
                                                            "index" : 0,
                                                            "name" : ""
                                                         },
                                                         {
                                                            "index" : -1,
                                                            "name" : "fun"
                                                         },
                                                         {
                                                            "index" : -1,
                                                            "name" : "min"
                                                         }
                                                      ],
                                                      "linkType" : "LT:CUSTOM_SLIDER",
                                                      "sliderValue" : -2
                                                   },
                                                   {
                                                      "linkPath" : [
                                                         {
                                                            "index" : -1,
                                                            "name" : "noise2d"
                                                         },
                                                         {
                                                            "index" : -1,
                                                            "name" : "fun"
                                                         },
                                                         {
                                                            "index" : -1,
                                                            "name" : "terms"
                                                         },
                                                         {
                                                            "index" : 0,
                                                            "name" : ""
                                                         },
                                                         {
                                                            "index" : -1,
                                                            "name" : "fun"
                                                         },
                                                         {
                                                            "index" : -1,
                                                            "name" : "fun"
                                                         },
                                                         {
                                                            "index" : -1,
                                                            "name" : "fun"
                                                         },
                                                         {
                                                            "index" : -1,
                                                            "name" : "base"
                                                         },
                                                         {
                                                            "index" : -1,
                                                            "name" : "cellScale"
                                                         }
                                                      ],
                                                      "linkType" : "LT:CUSTOM_SLIDER",
                                                      "sliderValue" : 5.5
                                                   },
                                                   {
                                                      "linkPath" : [
                                                         {
                                                            "index" : -1,
                                                            "name" : "noise2d"
                                                         },
                                                         {
                                                            "index" : -1,
                                                            "name" : "fun"
                                                         },
                                                         {
                                                            "index" : -1,
                                                            "name" : "terms"
                                                         },
                                                         {
                                                            "index" : 0,
                                                            "name" : ""
                                                         },
                                                         {
                                                            "index" : -1,
                                                            "name" : "fun"
                                                         },
                                                         {
                                                            "index" : -1,
                                                            "name" : "fun"
                                                         },
                                                         {
                                                            "index" : -1,
                                                            "name" : "fun"
                                                         },
                                                         {
                                                            "index" : -1,
                                                            "name" : "distortion"
                                                         },
                                                         {
                                                            "index" : -1,
                                                            "name" : "frequency"
                                                         },
                                                         {
                                                            "index" : -1,
                                                            "name" : "@xz"
                                                         }
                                                      ],
                                                      "linkType" : "LT:CUSTOM_SLIDER",
                                                      "sliderValue" : 1
                                                   }
                                                ],
                                                "offset" : [ 317.51583862304688, 366.33047485351563 ],
                                                "offset-hash" : "GXEbQl2WhE6mwtWX",
                                                "reference" : "noise2d/Heightmaps/Ditches.json",
                                                "tick" : 0,
                                                "type" : "reference"
                                             },
                                             "type" : "absolute"
                                          },
                                          "multiplier" : 1,
                                          "power" : 1
                                       },
                                       {
                                          "fun" : {
                                             "@collapsed" : false,
                                             "@name" : "Constant 2D",
                                             "@position" : [ 9738, 7490 ],
                                             "frequency" : [ 1, 1 ],
                                             "offset" : [ -276.82916259765625, 321.15682983398438 ],
                                             "offset-hash" : "6qIPujHIsn6speZx",
                                             "type" : "constant",
                                             "value" : -0.90800005197525024
                                          },
                                          "multiplier" : 1,
                                          "power" : 1
                                       },
                                       {
                                          "fun" : {
                                             "@collapsed" : false,
                                             "@name" : "Perlin 2D",
                                             "@position" : [ 9738, 7619 ],
                                             "frequency" : [ 0.53200000524520874, 0.53200000524520874 ],
                                             "offset" : [ -183.17539978027344, 257.05828857421875 ],
                                             "offset-hash" : "7ofummDecI3m7gJF",
                                             "type" : "perlin"
                                          },
                                          "multiplier" : 0.095000006258487701,
                                          "power" : 1
                                       }
                                    ],
                                    "type" : "sum"
                                 },
                                 {
                                    "@collapsed" : false,
                                    "@name" : "Constant 2D",
                                    "@position" : [ 9434, 7724 ],
                                    "frequency" : [ 1, 1 ],
                                    "offset" : [ 319.481201171875, 379.83905029296875 ],
                                    "offset-hash" : "vKMD9Xprx0GNHIfR",
                                    "type" : "constant",
                                    "value" : 0
                                 }
                              ],
                              "type" : "max"
                           },
                           "multiplier" : 0.87500005960464478,
                           "power" : 1
                        }
                     ],
                     "type" : "sum"
                  },
                  "heightmapMaxY" : {
                     "enabled" : false,
                     "value" : 256
                  },
                  "heightmapMinY" : {
                     "enabled" : false,
                     "value" : 0
                  },
                  "parts" : [],
                  "shrink" : null,
                  "strata" : {
                     "@collapsed" : false,
                     "@name" : "Join Strata",
                     "@position" : [ 8788, 8200 ],
                     "components" : [
                        {
                           "@collapsed" : false,
                           "@name" : "Fill1",
                           "@position" : [ 9084, 8134 ],
                           "links" : [],
                           "reference" : "strata/Fill1.json",
                           "tick" : 0,
                           "type" : "reference"
                        },
                        {
                           "@collapsed" : false,
                           "@name" : "Fill2",
                           "@position" : [ 9084, 8194 ],
                           "links" : [],
                           "reference" : "strata/Fill2.json",
                           "tick" : 0,
                           "type" : "reference"
                        },
                        {
                           "@collapsed" : false,
                           "@name" : "Fill3",
                           "@position" : [ 9084, 8254 ],
                           "links" : [],
                           "reference" : "strata/Fill3.json",
                           "tick" : 0,
                           "type" : "reference"
                        },
                        {
                           "@collapsed" : false,
                           "@name" : "Fill4",
                           "@position" : [ 9084, 8314 ],
                           "links" : [],
                           "reference" : "strata/Fill4.json",
                           "tick" : 0,
                           "type" : "reference"
                        },
                        {
                           "@collapsed" : false,
                           "@name" : "Fill5",
                           "@position" : [ 9084, 8374 ],
                           "links" : [],
                           "reference" : "strata/Fill5.json",
                           "tick" : 0,
                           "type" : "reference"
                        }
                     ],
                     "type" : "join"
                  },
                  "surface_decorations" : {
                     "@collapsed" : false,
                     "@name" : "Standard Decorations",
                     "@position" : [ 8788, 9448 ],
                     "@toggle-ceiling" : false,
                     "@toggle-floor" : true,
                     "ceiling" : [],
                     "floor" : [
                        {
                           "clearance" : 8,
                           "constraintType" : [
                              "GRASS_VERDANT_BASE/SOIL_CLAY_BASE",
                              "GRASS_VERDANT_BASE/SOIL_PEATY_BASE"
                           ],
                           "density" : -0.37000000476837158,
                           "depth" : 8,
                           "instance" : {
                              "@collapsed" : false,
                              "@name" : "Bush (deprecated)",
                              "@position" : [ 9099, 9453 ],
                              "blockType" : "WOOD_LUSH_LEAVES",
                              "height" : 1,
                              "maxScale" : 2,
                              "minScale" : 0.5,
                              "radius" : 6,
                              "stemType" : "WOOD_LUSH_LEAVES",
                              "taper" : 2,
                              "type" : "bush"
                           },
                           "maxGradient" : 5,
                           "maxSize" : 1,
                           "maxY" : 256,
                           "minGradient" : 3,
                           "minSize" : 0,
                           "minY" : 74,
                           "noise" : {
                              "@collapsed" : false,
                              "@name" : "Remap 2D",
                              "@position" : [ 9099, 9718 ],
                              "clamp" : true,
                              "clampPower" : 10,
                              "frequency" : [ 1, 1 ],
                              "fun" : {
                                 "@collapsed" : false,
                                 "@name" : "Remap 2D",
                                 "@position" : [ 9395, 9718 ],
                                 "clamp" : true,
                                 "clampPower" : 10,
                                 "frequency" : [ 1, 1 ],
                                 "fun" : {
                                    "@collapsed" : false,
                                    "@name" : "Sum 2D",
                                    "@position" : [ 9691, 9673 ],
                                    "frequency" : [ 1, 1 ],
                                    "terms" : [
                                       {
                                          "fun" : {
                                             "@collapsed" : false,
                                             "@name" : "Ditches",
                                             "@position" : [ 9987, 9663 ],
                                             "frequency" : [ 0.77500003576278687, 0.77500003576278687 ],
                                             "links" : [
                                                {
                                                   "linkPath" : [
                                                      {
                                                         "index" : -1,
                                                         "name" : "noise2d"
                                                      },
                                                      {
                                                         "index" : -1,
                                                         "name" : "fun"
                                                      },
                                                      {
                                                         "index" : -1,
                                                         "name" : "terms"
                                                      },
                                                      {
                                                         "index" : 0,
                                                         "name" : ""
                                                      },
                                                      {
                                                         "index" : -1,
                                                         "name" : "fun"
                                                      },
                                                      {
                                                         "index" : -1,
                                                         "name" : "min"
                                                      }
                                                   ],
                                                   "linkType" : "LT:CUSTOM_SLIDER",
                                                   "sliderValue" : -2
                                                },
                                                {
                                                   "linkPath" : [
                                                      {
                                                         "index" : -1,
                                                         "name" : "noise2d"
                                                      },
                                                      {
                                                         "index" : -1,
                                                         "name" : "fun"
                                                      },
                                                      {
                                                         "index" : -1,
                                                         "name" : "terms"
                                                      },
                                                      {
                                                         "index" : 0,
                                                         "name" : ""
                                                      },
                                                      {
                                                         "index" : -1,
                                                         "name" : "fun"
                                                      },
                                                      {
                                                         "index" : -1,
                                                         "name" : "fun"
                                                      },
                                                      {
                                                         "index" : -1,
                                                         "name" : "fun"
                                                      },
                                                      {
                                                         "index" : -1,
                                                         "name" : "base"
                                                      },
                                                      {
                                                         "index" : -1,
                                                         "name" : "cellScale"
                                                      }
                                                   ],
                                                   "linkType" : "LT:CUSTOM_SLIDER",
                                                   "sliderValue" : 8
                                                },
                                                {
                                                   "linkPath" : [
                                                      {
                                                         "index" : -1,
                                                         "name" : "noise2d"
                                                      },
                                                      {
                                                         "index" : -1,
                                                         "name" : "fun"
                                                      },
                                                      {
                                                         "index" : -1,
                                                         "name" : "terms"
                                                      },
                                                      {
                                                         "index" : 0,
                                                         "name" : ""
                                                      },
                                                      {
                                                         "index" : -1,
                                                         "name" : "fun"
                                                      },
                                                      {
                                                         "index" : -1,
                                                         "name" : "fun"
                                                      },
                                                      {
                                                         "index" : -1,
                                                         "name" : "fun"
                                                      },
                                                      {
                                                         "index" : -1,
                                                         "name" : "distortion"
                                                      },
                                                      {
                                                         "index" : -1,
                                                         "name" : "frequency"
                                                      },
                                                      {
                                                         "index" : -1,
                                                         "name" : "@xz"
                                                      }
                                                   ],
                                                   "linkType" : "LT:CUSTOM_SLIDER",
                                                   "sliderValue" : 0.12600000202655792
                                                }
                                             ],
                                             "offset" : [ -103.05943298339844, 61.666439056396484 ],
                                             "offset-hash" : "Kd4RC7kMUiKmP39d",
                                             "reference" : "noise2d/Heightmaps/Ditches.json",
                                             "tick" : 0,
                                             "type" : "reference"
                                          },
                                          "multiplier" : -1,
                                          "power" : 1
                                       },
                                       {
                                          "fun" : {
                                             "@collapsed" : false,
                                             "@name" : "Constant 2D",
                                             "@position" : [ 9987, 9838 ],
                                             "frequency" : [ 1, 1 ],
                                             "offset" : [ -170.65080261230469, 156.39212036132813 ],
                                             "offset-hash" : "IygjzaWrzolH6AcY",
                                             "type" : "constant",
                                             "value" : -0.21800000965595245
                                          },
                                          "multiplier" : 1,
                                          "power" : 1
                                       }
                                    ],
                                    "type" : "sum"
                                 },
                                 "max" : 2,
                                 "min" : -2,
                                 "type" : "remap"
                              },
                              "max" : 2,
                              "min" : -2,
                              "type" : "remap"
                           },
                           "placementType" : "FLORA_FLOWER_1",
                           "sizeNoise" : null,
                           "smooth" : false,
                           "threshold" : 0
                        }
                     ],
                     "type" : "standard"
                  },
                  "surface_substrate" : {
                     "@collapsed" : false,
                     "@name" : "Standard Substrate",
                     "@position" : [ 8788, 8434 ],
                     "strates" : [
                        {
                           "averageDepth" : 3,
                           "blockType" : "GRASS_VERDANT_BASE/SOIL_PEATY_BASE",
                           "depthNoise" : {
                              "@collapsed" : false,
                              "@name" : "Perlin 2D",
                              "@position" : [ 9093, 8729 ],
                              "frequency" : [ 1, 1 ],
                              "offset" : [ -391.5526123046875, -283.49493408203125 ],
                              "offset-hash" : "eOnm2yo7kTcW7QTr",
                              "type" : "perlin"
                           },
                           "depthNoiseScale" : 6,
                           "maxGradient" : 5,
                           "maxY" : 256,
                           "metadata" : {
                              "@toggle-metadata" : true,
                              "maxGradient" : 5,
                              "maxThreshold" : 1,
                              "maxY" : 256,
                              "minGradient" : 0,
                              "minThreshold" : -1,
                              "minY" : 0,
                              "noise" : {
                                 "@collapsed" : false,
                                 "@name" : "Perlin 2D",
                                 "@position" : [ 9093, 8835 ],
                                 "frequency" : [ 1, 1 ],
                                 "offset" : [ -71.393913269042969, -233.91595458984375 ],
                                 "offset-hash" : "vfKUd1LeyNQkxZRE",
                                 "type" : "perlin"
                              }
                           },
                           "minGradient" : 0,
                           "minY" : 0
                        },
                        {
                           "averageDepth" : 3,
                           "blockType" : "GRASS_VERDANT_BASE/SOIL_CLAY_BASE",
                           "depthNoise" : {
                              "@collapsed" : false,
                              "@name" : "Perlin 2D",
                              "@position" : [ 9093, 8941 ],
                              "frequency" : [ 1, 1 ],
                              "offset" : [ 161.94705200195313, -330.5015869140625 ],
                              "offset-hash" : "AIGhRCqESy8alDUl",
                              "type" : "perlin"
                           },
                           "depthNoiseScale" : 6,
                           "maxGradient" : 5,
                           "maxY" : 256,
                           "metadata" : {
                              "@toggle-metadata" : true,
                              "maxGradient" : 5,
                              "maxThreshold" : 1,
                              "maxY" : 256,
                              "minGradient" : 0,
                              "minThreshold" : -1,
                              "minY" : 0,
                              "noise" : {
                                 "@collapsed" : false,
                                 "@name" : "Perlin 2D",
                                 "@position" : [ 9093, 9047 ],
                                 "frequency" : [ 1, 1 ],
                                 "offset" : [ -360.7171630859375, 44.172367095947266 ],
                                 "offset-hash" : "OJ8w10KkTsL3D1GY",
                                 "type" : "perlin"
                              }
                           },
                           "minGradient" : 0,
                           "minY" : 0
                        },
                        {
                           "averageDepth" : 3,
                           "blockType" : "GRAVEL_DEFAULT_BASE",
                           "depthNoise" : null,
                           "depthNoiseScale" : 6,
                           "maxGradient" : 5,
                           "maxY" : 256,
                           "metadata" : {
                              "@toggle-metadata" : true,
                              "maxGradient" : 5,
                              "maxThreshold" : 1,
                              "maxY" : 256,
                              "minGradient" : 0,
                              "minThreshold" : -1,
                              "minY" : 0,
                              "noise" : null
                           },
                           "minGradient" : 0,
                           "minY" : 0
                        }
                     ],
                     "type" : "standard"
                  },
                  "threeD" : null,
                  "threeDMaxY" : {
                     "enabled" : false,
                     "value" : 256
                  },
                  "threeDMinY" : {
                     "enabled" : false,
                     "value" : 0
                  },
                  "threeDSurfaceMaxY" : {
                     "enabled" : false,
                     "value" : 256
                  },
                  "threeDSurfaceMinY" : {
                     "enabled" : false,
                     "value" : 0
                  },
                  "threeDThresholdBias" : {
                     "enabled" : false,
                     "value" : -1
                  },
                  "threed_decorations" : null,
                  "threed_substrate" : null,
                  "x" : null,
                  "y" : null
               },
               "temperature" : {
                  "enabled" : true,
                  "value" : 0.52600002288818359
               },
               "vegetation" : {
                  "enabled" : true,
                  "value" : 0.23800000548362732
               },
               "weight" : 0.5
            },
            "links" : [
               {
                  "blockConstraint" : 3274820576,
                  "blockDefault" : "",
                  "checkDefault" : false,
                  "linkPath" : [
                     {
                        "index" : -1,
                        "name" : "biome"
                     },
                     {
                        "index" : -1,
                        "name" : "fun"
                     },
                     {
                        "index" : -1,
                        "name" : "weight"
                     }
                  ],
                  "linkType" : "LT:CUSTOM_SLIDER",
                  "name" : "Biome Weight",
                  "shortPath" : "SinkHoles.weight",
                  "sliderCheck" : false,
                  "sliderDefault" : 0.5,
                  "sliderMax" : 1,
                  "sliderMin" : 0,
                  "sliderStep" : 0.0010000000474974513
               }
            ]
         },
         "generator" : {
            "@version" : 6,
            "biomeSize" : 24,
            "lowerSea" : {
               "level" : 16,
               "liquidType" : "WATER"
            },
            "sea" : {
               "level" : 64,
               "liquidType" : "WATER"
            }
         },
         "seed" : "I has a seed!",
         "sharedConfig" : {
            "blockColors" : {
               "ASH_DEFAULT_BASE" : 1,
               "CRYSTAL_GLEAM_BASE" : 13,
               "FLORA_FLOWER_1" : 1,
               "FLORA_FLOWER_2" : 1,
               "FLORA_FLOWER_3" : 1,
               "FLORA_FLOWER_4" : 1,
               "FLORA_PLANT_FIBROUS" : 1,
               "FLORA_PLANT_INKY" : 1,
               "GRASS_BARBED_BASE" : 8,
               "GRASS_GNARLED_BASE" : 7,
               "GRASS_VERDANT_BASE" : 9,
               "GRAVEL_DEFAULT_BASE" : 5,
               "GROWTH_DEFAULT_BASE" : 1,
               "MOULD_DEFAULT_BASE" : 1,
               "MUD_DEFAULT_BASE" : 1,
               "ROCK_IGNEOUS_BASE" : 4,
               "ROCK_METAMORPHIC_BASE" : 5,
               "ROCK_SEDIMENTARY_BASE" : 6,
               "SAND_DEFAULT_BASE" : 16,
               "SOIL_CLAY_BASE" : 1,
               "SOIL_PEATY_BASE" : 3,
               "SOIL_SILTY_BASE" : 2,
               "SPONGE_DEFAULT_BASE" : 1,
               "TANGLE_DEFAULT_BASE" : 1,
               "THORNS_DEFAULT_BASE" : 1,
               "WOOD_ANCIENT_TRUNK" : 10,
               "WOOD_EXOTIC_LEAVES" : 15,
               "WOOD_LUSH_LEAVES" : 13,
               "WOOD_LUSTROUS_TRUNK" : 1,
               "WOOD_TWISTED_TRUNK" : 11,
               "WOOD_WAXY_LEAVES" : 13
            },
            "worldSize" : 288
         },
         "test" : {
            "@collapsed" : false,
            "@name" : "Reference Biome",
            "@position" : [ 7844, 9969 ],
            "type" : "reference"
         }
      },
      "links" : [],
      "reference" : "",
      "tick" : 0,
      "type" : "reference"
   }
}
